tracewrapper/__init__.py
tracewrapper/tracewrapper.py
tracewrapper-0.0.8.dist-info/LICENSE
tracewrapper-0.0.8.dist-info/METADATA
tracewrapper-0.0.8.dist-info/WHEEL
tracewrapper-0.0.8.dist-info/top_level.txt
tracewrapper-0.0.8.dist-info/RECORD
