Metadata-Version: 2.1
Name: tracewrapper
Version: 0.0.8
Summary: A wrapper for sys.settrace to enable programs to have more than one trace active.
Home-page: https://github.com/BigIan1969/Tracewrapper
Author: Ian Holdsworth
Author-email: Ian.Holdsworth@gmail.com
License: UNKNOWN
Project-URL: Bug Tracker, https://github.com/BigIan1969/Tracewrapper
Platform: UNKNOWN
Classifier: Programming Language :: Python :: 3
Classifier: License :: OSI Approved :: MIT License
Classifier: Operating System :: OS Independent
Requires-Python: >=3.6
License-File: LICENSE
